envelopes/__init__.py
envelopes/cerfcpp.dll
envelopes/envelopes_cpp.cp311-win_amd64.pyd
envelopes/envelopes_cpp.pyi
envelopes/envelopes_py.py
envelopes_qc-0.0.7.dist-info/licenses/LICENSE
envelopes_qc-0.0.7.dist-info/METADATA
envelopes_qc-0.0.7.dist-info/WHEEL
envelopes_qc-0.0.7.dist-info/top_level.txt
envelopes_qc-0.0.7.dist-info/RECORD
