Metadata-Version: 2.4
Name: envelopes-qc
Version: 0.0.7
Summary: Envelops impelemented by C++ and Python.
Author-email: Shibo Xu <sbxu@zju.edu.cn>
Classifier: Programming Language :: Python :: 3
Classifier: Operating System :: Microsoft :: Windows
Requires-Python: >=3.9
License-File: LICENSE
Requires-Dist: numpy>=1.13.3
Requires-Dist: scipy>=1.0.0
Dynamic: license-file
